<?xml version="1.0"?>
<?iotk version="1.2.0"?>
<?iotk file_version="1.0"?>
<?iotk binary="F"?>
<?iotk qe_syntax="F"?>
<Root>
  <PM_HEADER>
    <DONE_IRR type="logical" size="1">
T
    </DONE_IRR>
  </PM_HEADER>
  <PARTIAL_MATRIX>
    <PARTIAL_DYN type="complex" size="36">
-3.887904732111159E+000,-1.893566845862573E-007
 1.832503824377906E-003, 1.157204114156303E-006
 7.682265781824292E-003, 5.927452421807660E-008
 0.000000000000000E+000, 0.000000000000000E+000
 0.000000000000000E+000, 0.000000000000000E+000
 0.000000000000000E+000, 0.000000000000000E+000
 4.585246681551001E-003,-1.198861879156042E-006
-3.851568621331830E+000,-1.844262300379143E-007
 2.821404582431763E-002, 6.040887811685140E-007
 0.000000000000000E+000, 0.000000000000000E+000
 0.000000000000000E+000, 0.000000000000000E+000
 0.000000000000000E+000, 0.000000000000000E+000
 8.022955167551939E-003, 2.723104346084611E-009
 2.873596206301761E-002,-4.181188833044495E-007
-3.833641424331947E+000,-6.284874384924799E-008
 0.000000000000000E+000, 0.000000000000000E+000
 0.000000000000000E+000, 0.000000000000000E+000
 0.000000000000000E+000, 0.000000000000000E+000
-1.243530742001944E-007, 2.569371650700273E-002
-7.171470011609320E-007,-1.744510686472175E-002
 5.466455263841469E-006, 7.449675963358699E-003
 0.000000000000000E+000, 0.000000000000000E+000
 0.000000000000000E+000, 0.000000000000000E+000
 0.000000000000000E+000, 0.000000000000000E+000
-3.562064364914796E-006,-8.892258634214450E-003
 2.399455123685418E-006,-1.399681927534836E-002
 6.488577243390480E-007, 1.867289869004697E-002
 0.000000000000000E+000, 0.000000000000000E+000
 0.000000000000000E+000, 0.000000000000000E+000
 0.000000000000000E+000, 0.000000000000000E+000
 6.906827554912717E-007,-1.951076624085016E-002
 5.273736160454293E-006, 3.080815749563194E-002
 1.040280073115745E-006, 6.997208485193157E-003
 0.000000000000000E+000, 0.000000000000000E+000
 0.000000000000000E+000, 0.000000000000000E+000
 0.000000000000000E+000, 0.000000000000000E+000
    </PARTIAL_DYN>
    <PARTIAL_ZUE type="complex" size="18">
-2.843311707263507E-005, 5.383486438136648E-002
 2.261857872368344E-005, 2.229316921548979E-001
 6.876953504763610E-006, 3.441149499443789E-001
 0.000000000000000E+000, 0.000000000000000E+000
 0.000000000000000E+000, 0.000000000000000E+000
 0.000000000000000E+000, 0.000000000000000E+000
-3.838791905710610E-005,-1.352056442879910E-001
 3.489745206827302E-005, 5.221031620656330E-002
-3.285430503928355E-005,-4.334280717076401E-001
 0.000000000000000E+000, 0.000000000000000E+000
 0.000000000000000E+000, 0.000000000000000E+000
 0.000000000000000E+000, 0.000000000000000E+000
 4.544209912848647E-006, 1.572408619421939E-001
 3.048928023134182E-005, 3.160540512797655E-001
-5.824277420126730E-006,-2.654687942149545E-002
 0.000000000000000E+000, 0.000000000000000E+000
 0.000000000000000E+000, 0.000000000000000E+000
 0.000000000000000E+000, 0.000000000000000E+000
    </PARTIAL_ZUE>
  </PARTIAL_MATRIX>
</Root>

