<?xml version="1.0"?>
<?iotk version="1.2.0"?>
<?iotk file_version="1.0"?>
<?iotk binary="F"?>
<?iotk qe_syntax="F"?>
<Root>
  <PM_HEADER>
    <DONE_IRR type="logical" size="1">
T
    </DONE_IRR>
  </PM_HEADER>
  <PARTIAL_MATRIX>
    <PARTIAL_DYN type="complex" size="36">
 0.000000000000000E+000, 0.000000000000000E+000
 0.000000000000000E+000, 0.000000000000000E+000
-5.877636680156522E-003,-1.135905680683051E-002
 4.285540123660529E-003,-1.851825857083300E-002
 0.000000000000000E+000, 0.000000000000000E+000
 0.000000000000000E+000, 0.000000000000000E+000
 0.000000000000000E+000, 0.000000000000000E+000
 0.000000000000000E+000, 0.000000000000000E+000
-1.946713440689629E-003,-2.132890124400175E-002
 7.008769967356950E-003,-4.126964181116739E-003
 0.000000000000000E+000, 0.000000000000000E+000
 0.000000000000000E+000, 0.000000000000000E+000
 0.000000000000000E+000, 0.000000000000000E+000
 0.000000000000000E+000, 0.000000000000000E+000
-2.909798752937559E+000,-2.436255941054175E-004
-1.492778155732852E-002, 1.612229245249153E-003
 0.000000000000000E+000, 0.000000000000000E+000
 0.000000000000000E+000, 0.000000000000000E+000
 0.000000000000000E+000, 0.000000000000000E+000
 0.000000000000000E+000, 0.000000000000000E+000
-1.492778019860987E-002,-1.429330651835881E-003
-2.898592267012690E+000, 2.436253259878348E-004
 0.000000000000000E+000, 0.000000000000000E+000
 0.000000000000000E+000, 0.000000000000000E+000
 0.000000000000000E+000, 0.000000000000000E+000
 0.000000000000000E+000, 0.000000000000000E+000
 4.428762905639099E-003,-7.675877988976776E-003
 3.618620103652391E-003, 1.775314816778027E-003
 0.000000000000000E+000, 0.000000000000000E+000
 0.000000000000000E+000, 0.000000000000000E+000
 0.000000000000000E+000, 0.000000000000000E+000
 0.000000000000000E+000, 0.000000000000000E+000
-1.729764397061315E-002, 1.102058601606563E-002
-1.183349834657439E-002,-1.843914365246983E-002
 0.000000000000000E+000, 0.000000000000000E+000
 0.000000000000000E+000, 0.000000000000000E+000
    </PARTIAL_DYN>
  </PARTIAL_MATRIX>
</Root>

