<?xml version="1.0"?>
<?iotk version="1.2.0"?>
<?iotk file_version="1.0"?>
<?iotk binary="F"?>
<?iotk qe_syntax="F"?>
<Root>
  <PM_HEADER>
    <DONE_IRR type="logical" size="1">
T
    </DONE_IRR>
  </PM_HEADER>
  <PARTIAL_MATRIX>
    <PARTIAL_DYN type="complex" size="36">
 0.000000000000000E+000, 0.000000000000000E+000
 0.000000000000000E+000, 0.000000000000000E+000
 0.000000000000000E+000, 0.000000000000000E+000
-5.914773105325510E-008,-5.899508257447125E-003
 8.605923883416022E-008,-1.536965120961350E-002
 4.103312718330490E-007,-1.730964049756391E-002
 0.000000000000000E+000, 0.000000000000000E+000
 0.000000000000000E+000, 0.000000000000000E+000
 0.000000000000000E+000, 0.000000000000000E+000
 5.214874587711193E-009,-2.044821034973833E-002
-2.040967670771665E-007, 1.970267206055233E-002
-2.555097554047744E-007, 1.114876400173399E-002
 0.000000000000000E+000, 0.000000000000000E+000
 0.000000000000000E+000, 0.000000000000000E+000
 0.000000000000000E+000, 0.000000000000000E+000
 2.705306750457048E-007, 1.192152388544215E-002
-2.069897144518773E-007, 9.484716603906051E-003
-1.454002103440377E-007,-3.350112728985034E-002
 0.000000000000000E+000, 0.000000000000000E+000
 0.000000000000000E+000, 0.000000000000000E+000
 0.000000000000000E+000, 0.000000000000000E+000
-3.609153451006665E+000, 8.078139298690082E-008
-3.222253961510671E-003, 9.138991215309699E-008
-5.318320410919774E-002, 3.764042485422785E-008
 0.000000000000000E+000, 0.000000000000000E+000
 0.000000000000000E+000, 0.000000000000000E+000
 0.000000000000000E+000, 0.000000000000000E+000
-3.224779764645435E-003,-9.209585542715661E-008
-3.496640005577893E+000, 8.179918163227300E-008
 9.980053124095813E-003, 3.677361174726886E-008
 0.000000000000000E+000, 0.000000000000000E+000
 0.000000000000000E+000, 0.000000000000000E+000
 0.000000000000000E+000, 0.000000000000000E+000
-5.318469737176967E-002,-3.575166474672856E-008
 9.985989144613499E-003,-3.221396777967384E-008
-3.479488483013756E+000, 9.273687901334092E-008
    </PARTIAL_DYN>
    <PARTIAL_ZUE type="complex" size="18">
 0.000000000000000E+000, 0.000000000000000E+000
 0.000000000000000E+000, 0.000000000000000E+000
 0.000000000000000E+000, 0.000000000000000E+000
-3.410617436926748E+000, 2.629357641238548E-007
 1.935430015267028E+000,-2.101542722740930E-007
-1.606907092708391E+000, 6.150734049781578E-007
 0.000000000000000E+000, 0.000000000000000E+000
 0.000000000000000E+000, 0.000000000000000E+000
 0.000000000000000E+000, 0.000000000000000E+000
 2.092327372772314E+000,-9.047947187610940E-008
 2.833132986951816E+000,-2.856514077641971E-007
-1.271485916602896E+000, 9.441626911742151E-007
 0.000000000000000E+000, 0.000000000000000E+000
 0.000000000000000E+000, 0.000000000000000E+000
 0.000000000000000E+000, 0.000000000000000E+000
-6.904839116141773E-001, 8.005503766594321E-007
-2.608221997082315E-001, 2.700861486182063E-007
-3.049545949115470E+000, 4.326975055445004E-007
    </PARTIAL_ZUE>
  </PARTIAL_MATRIX>
</Root>

