<?xml version="1.0"?>
<?iotk version="1.2.0"?>
<?iotk file_version="1.0"?>
<?iotk binary="F"?>
<?iotk qe_syntax="F"?>
<Root>
  <PM_HEADER>
    <DONE_IRR type="logical" size="1">
T
    </DONE_IRR>
  </PM_HEADER>
  <PARTIAL_MATRIX>
    <PARTIAL_DYN type="complex" size="36">
 4.825867908147627E+000,-2.317232537212744E-016
 1.114740580426945E-002,-1.246708894535184E-002
 4.675814365874775E-003, 4.214742363545240E-002
 1.676972248934560E-002,-3.994156644116795E-003
 7.466054916642074E-002,-2.262365158387205E-001
 6.037015228991127E-001,-1.130435508290675E+000
 1.114740580426943E-002, 1.246708894535210E-002
 4.825832348487365E+000, 3.918517648673492E-016
 1.425448706397631E-002,-3.023973680946656E-003
-3.546727148571509E-002, 2.529645477695869E-002
 9.856866217567519E-001,-8.428802334289212E-001
-6.429256807533214E-002, 1.131216074544368E-001
 4.675814365874831E-003,-4.214742363545212E-002
 1.425448706397580E-002, 3.023973680946465E-003
 4.486064207141438E+000, 4.376988400230248E-016
 2.147391734125381E-004, 1.961657081380339E-003
 5.826165706430424E-002, 4.653117383609429E-002
-2.749225749631723E-003, 3.190677265799025E-003
 1.676972248934551E-002, 3.994156644116323E-003
-3.546727148571482E-002,-2.529645477695867E-002
 2.147391734124617E-004,-1.961657081380480E-003
 4.485993322791025E+000,-3.851467559603099E-016
 1.022059219050401E-002, 4.914307456646574E-003
 7.266159892125142E-002,-1.285478245476609E-003
 7.466054916642120E-002, 2.262365158387209E-001
 9.856866217567518E-001, 8.428802334289219E-001
 5.826165706430485E-002,-4.653117383609440E-002
 1.022059219050429E-002,-4.914307456647353E-003
 3.909607628008628E+000,-9.923078236216319E-017
-1.458966154301954E-002,-1.098130154681231E-002
 6.037015228991132E-001, 1.130435508290675E+000
-6.429256807533186E-002,-1.131216074544364E-001
-2.749225749630807E-003,-3.190677265798831E-003
 7.266159892125193E-002, 1.285478245476687E-003
-1.458966154301948E-002, 1.098130154681203E-002
 3.917712451030688E+000,-5.688581389516722E-018
    </PARTIAL_DYN>
  </PARTIAL_MATRIX>
</Root>

