<?xml version="1.0"?>
<?iotk version="1.2.0"?>
<?iotk file_version="1.0"?>
<?iotk binary="F"?>
<?iotk qe_syntax="F"?>
<Root>
  <PM_HEADER>
    <DONE_IRR type="logical" size="1">
T
    </DONE_IRR>
  </PM_HEADER>
  <PARTIAL_MATRIX>
    <PARTIAL_DYN type="complex" size="36">
 0.000000000000000E+000, 0.000000000000000E+000
 0.000000000000000E+000, 0.000000000000000E+000
 0.000000000000000E+000, 0.000000000000000E+000
 8.866232828648457E-008,-5.684849411179539E-003
-3.214312029459210E-007,-1.501651872438090E-002
-1.053776890378409E-007,-1.765122132185926E-002
 0.000000000000000E+000, 0.000000000000000E+000
 0.000000000000000E+000, 0.000000000000000E+000
 0.000000000000000E+000, 0.000000000000000E+000
 7.978033047389976E-008,-1.994035320918224E-002
 1.041010609242887E-007, 1.964029268815678E-002
 1.548063537464006E-007, 1.141132231473604E-002
 0.000000000000000E+000, 0.000000000000000E+000
 0.000000000000000E+000, 0.000000000000000E+000
 0.000000000000000E+000, 0.000000000000000E+000
 3.535095689129186E-007, 1.195940572351928E-002
-5.310092189569904E-008, 9.496802455385334E-003
 2.271534037881495E-007,-3.375075226466336E-002
 0.000000000000000E+000, 0.000000000000000E+000
 0.000000000000000E+000, 0.000000000000000E+000
 0.000000000000000E+000, 0.000000000000000E+000
-3.608978860534049E+000,-2.526016061370176E-008
-3.101921940504068E-003, 5.420892935385701E-008
-5.309678253337544E-002, 2.941865906880274E-008
 0.000000000000000E+000, 0.000000000000000E+000
 0.000000000000000E+000, 0.000000000000000E+000
 0.000000000000000E+000, 0.000000000000000E+000
-3.104397754827241E-003,-4.730716682981673E-008
-3.496789230122086E+000,-1.597260528919028E-008
 1.000593378376996E-002, 9.831741224431627E-008
 0.000000000000000E+000, 0.000000000000000E+000
 0.000000000000000E+000, 0.000000000000000E+000
 0.000000000000000E+000, 0.000000000000000E+000
-5.309793099268684E-002,-1.886530736768985E-008
 1.001220220242378E-002,-1.033087679242086E-007
-3.480082505744074E+000,-2.964561021404201E-008
    </PARTIAL_DYN>
    <PARTIAL_ZUE type="complex" size="18">
 0.000000000000000E+000, 0.000000000000000E+000
 0.000000000000000E+000, 0.000000000000000E+000
 0.000000000000000E+000, 0.000000000000000E+000
-3.412323381995958E+000,-6.891150110305586E-007
 1.936235658969307E+000, 7.388955237644972E-007
-1.608286199448310E+000,-9.115206827150757E-007
 0.000000000000000E+000, 0.000000000000000E+000
 0.000000000000000E+000, 0.000000000000000E+000
 0.000000000000000E+000, 0.000000000000000E+000
 2.091210260678484E+000,-2.386831173460427E-008
 2.831932163024799E+000, 6.783665838959222E-007
-1.273024587355790E+000,-7.635488072866096E-007
 0.000000000000000E+000, 0.000000000000000E+000
 0.000000000000000E+000, 0.000000000000000E+000
 0.000000000000000E+000, 0.000000000000000E+000
-6.905160805045127E-001,-7.935089623059424E-007
-2.601229363728216E-001, 1.843784531475462E-007
-3.051628388913906E+000, 2.433172058932402E-007
    </PARTIAL_ZUE>
  </PARTIAL_MATRIX>
</Root>

