<?xml version="1.0"?>
<?iotk version="1.2.0"?>
<?iotk file_version="1.0"?>
<?iotk binary="F"?>
<?iotk qe_syntax="F"?>
<Root>
  <PM_HEADER>
    <DONE_IRR type="logical" size="1">
T
    </DONE_IRR>
  </PM_HEADER>
  <PARTIAL_MATRIX>
    <PARTIAL_DYN type="complex" size="36">
 5.442271092708614E+000,-9.177526356655868E-017
 2.236984522523937E-002, 8.956268206539370E-004
 1.025610158303768E-002, 5.652040682039540E-004
-1.624308206769755E-003, 2.858389159323309E-003
-4.953290239866448E-002,-1.690710034683690E-003
 4.984884907197148E-002,-2.878934782181901E-003
 2.236984522523937E-002,-8.956268206540274E-004
 5.442271092708607E+000,-1.302097443646194E-016
-1.581917996956614E-003, 2.894557444814753E-003
-1.026272538281515E-002,-3.337385556371559E-004
 4.277665489354539E-002,-2.043798524903131E-003
 5.575458698577436E-002, 2.640010130859456E-003
 1.025610158303759E-002,-5.652040682039268E-004
-1.581917996956663E-003,-2.894557444814829E-003
 3.052799857944561E+000,-1.064917164676176E-016
 2.232413231324875E-002,-3.293827967787685E-005
 6.382897439225382E-002,-1.674815711851727E-003
-3.464609857703398E-002,-1.844936924270320E-003
-1.624308206769743E-003,-2.858389159323379E-003
-1.026272538281576E-002, 3.337385556370889E-004
 2.232413231324870E-002, 3.293827967777898E-005
 3.038497364445717E+000,-1.155053991374930E-016
 4.139465026783933E-002, 2.527691362304221E-003
 5.572323278989739E-002,-1.106378689894460E-003
-4.953290239866445E-002, 1.690710034683713E-003
 4.277665489354535E-002, 2.043798524903223E-003
 6.382897439225385E-002, 1.674815711851972E-003
 4.139465026783933E-002,-2.527691362304563E-003
 4.954270592895942E+000,-1.597316350909244E-016
 5.703424217276959E-005, 3.432791739664865E-003
 4.984884907197150E-002, 2.878934782182200E-003
 5.575458698577437E-002,-2.640010130859747E-003
-3.464609857703396E-002, 1.844936924270388E-003
 5.572323278989733E-002, 1.106378689894505E-003
 5.703424217321400E-005,-3.432791739664824E-003
 4.953382768848427E+000,-1.543748959148024E-016
    </PARTIAL_DYN>
  </PARTIAL_MATRIX>
</Root>

