<?xml version="1.0"?>
<?iotk version="1.2.0"?>
<?iotk file_version="1.0"?>
<?iotk binary="F"?>
<?iotk qe_syntax="F"?>
<Root>
  <PM_HEADER>
    <DONE_IRR type="logical" size="1">
T
    </DONE_IRR>
  </PM_HEADER>
  <PARTIAL_MATRIX>
    <PARTIAL_DYN type="complex" size="36">
 4.547790241259804E+000,-1.028349994104269E-016
 1.572818956816932E-001, 1.668512097354093E-009
 9.302519913746540E-002, 1.596046860522861E-010
 9.428781686468828E-007,-1.268513562314647E-004
-1.295544584907667E-006,-8.076296752050794E-006
-4.154978547623378E-007, 1.806175622192109E-004
 1.572818956816932E-001,-1.668512415388844E-009
 4.458147371575065E+000,-2.010663585305419E-016
 3.073625466944261E-002,-8.470098772718191E-010
 5.456262574841464E-007,-1.138813155572741E-004
-8.442820125793664E-007,-2.278664480956186E-004
 6.132011842963908E-007,-1.157972220553543E-004
 9.302519913746540E-002,-1.596046328171166E-010
 3.073625466944266E-002, 8.470099270511800E-010
 4.435120503811349E+000,-5.942635386149275E-017
 2.049732089800735E-006,-1.371830787499688E-004
-4.836961521141603E-007,-2.280555972399515E-005
 7.753759298468954E-007, 3.650432522349258E-004
 9.428781685345594E-007, 1.268513562312433E-004
 5.456262575162388E-007, 1.138813155570388E-004
 2.049732089696651E-006, 1.371830787500688E-004
 3.725910290071718E+000,-2.607896572551813E-016
 4.707058483449855E-003, 4.356760305240050E-010
 1.234022935239214E-001,-2.861551199048876E-010
-1.295544584921544E-006, 8.076296751986596E-006
-8.442820126973276E-007, 2.278664480954227E-004
-4.836961518921157E-007, 2.280555972394384E-005
 4.707058483449820E-003,-4.356762533218373E-010
 3.478453098318573E+000,-1.147500286132789E-016
-2.122397161010174E-002, 2.072942871432560E-010
-4.154978547348262E-007,-1.806175622190335E-004
 6.132011842348352E-007, 1.157972220551934E-004
 7.753759299017560E-007,-3.650432522349973E-004
 1.234022935239215E-001, 2.861550774548167E-010
-2.122397161010177E-002,-2.072943249548002E-010
 3.447201445438735E+000, 1.221197406599863E-017
    </PARTIAL_DYN>
  </PARTIAL_MATRIX>
</Root>

