<?xml version="1.0"?>
<?iotk version="1.2.0"?>
<?iotk file_version="1.0"?>
<?iotk binary="F"?>
<?iotk qe_syntax="F"?>
<Root>
  <PM_HEADER>
    <DONE_IRR type="logical" size="1">
T
    </DONE_IRR>
  </PM_HEADER>
  <PARTIAL_MATRIX>
    <PARTIAL_DYN type="complex" size="36">
 3.705831611403539E+000, 4.105301820731177E-017
 2.908263907475117E-015,-2.638164074855049E-003
 5.060513640076092E-016,-2.060244619753297E-004
 1.255641641009775E-015,-1.389534949317789E-003
 7.342325066219049E-002,-3.815755454829603E-019
-2.649746558346241E-002,-1.214350213129638E-017
 2.908263907475117E-015, 2.638164074855376E-003
 6.824500672995987E+000, 4.105312412520429E-017
 6.222693348932632E-002,-9.620296590296474E-018
 4.646026507638417E-002,-7.997725784464759E-019
 4.909369080968035E-016,-2.559210192838073E-003
-2.898492535395591E-015, 4.796083708632583E-003
 4.227846371607225E-016, 2.060244619751881E-004
 6.222693348932624E-002, 3.219639985967653E-019
 3.345608923950611E+000,-1.930417118372782E-016
-3.098528810109790E-002,-2.166505073231002E-017
 3.498937251045220E-015, 3.690357894725993E-004
 4.996003610813204E-016,-6.165944896473556E-004
 1.144619338547259E-015, 1.389534949317844E-003
 4.646026507638425E-002, 3.298921874632420E-017
-3.098528810109818E-002,-1.107615932884024E-017
 3.254073243897123E+000,-2.006492998021611E-016
 5.282232984349378E-016, 1.262919947678367E-003
-3.427813588530171E-015,-9.967316488281562E-004
 7.342325066219038E-002, 3.471908788753666E-019
 9.211483301390516E-016, 2.559210192837929E-003
 3.707104068162437E-015,-3.690357894725401E-004
 6.947567521287112E-016,-1.262919947678176E-003
 4.876349861726142E+000,-2.031078069837168E-016
 5.017442506216329E-002, 1.963268903600863E-017
-2.649746558346252E-002,-2.149966970035415E-017
-2.842981384164334E-015,-4.796083708632497E-003
 5.273559366969494E-016, 6.165944896473527E-004
-4.232725281383409E-015, 9.967316488284793E-004
 5.017442506216321E-002, 1.202220400683177E-017
 4.836967427321518E+000,-1.911354966103429E-016
    </PARTIAL_DYN>
  </PARTIAL_MATRIX>
</Root>

