<?xml version="1.0"?>
<?iotk version="1.2.0"?>
<?iotk file_version="1.0"?>
<?iotk binary="F"?>
<?iotk qe_syntax="F"?>
<Root>
  <PM_HEADER>
    <DONE_IRR type="logical" size="1">
T
    </DONE_IRR>
  </PM_HEADER>
  <PARTIAL_MATRIX>
    <PARTIAL_DYN type="complex" size="36">
 5.286983753105609E+000,-9.087527739140813E-017
 1.270843181955326E+000,-3.618996484704936E-001
 5.610821149385400E-002,-2.149457544418485E-004
-4.123958563981918E-002,-2.328490737609187E-003
 1.066074767352043E-003, 6.690533397459418E-004
-1.693926416726672E-003,-3.186318203003310E-004
 1.270843181955326E+000, 3.618996484704936E-001
 5.286983753105611E+000, 1.105490560656564E-016
-6.192729348199826E-004, 4.031444738335703E-004
-1.358734693250655E-003,-1.470672064730674E-003
 3.305668720529698E-002, 4.761987194818332E-002
 2.972296739141515E-002,-2.470731324272332E-002
 5.610821149385372E-002, 2.149457544423869E-004
-6.192729348211481E-004,-4.031444738333242E-004
 4.061901190754496E+000, 1.204304509821106E-016
 3.912377687197494E-002,-4.189946930845294E-005
-3.713186593250518E-001,-7.119435018454585E-002
-4.971080240233406E-001, 2.233630050548643E-001
-4.123958563981746E-002, 2.328490737608874E-003
-1.358734693249738E-003, 1.470672064730730E-003
 3.912377687197603E-002, 4.189946930814515E-005
 3.877568458927795E+000,-6.470844331726592E-017
 1.765846250786074E-001, 5.167078202390170E-001
-3.048515562099072E-001,-2.236905085621607E-001
 1.066074767351420E-003,-6.690533397450224E-004
 3.305668720529637E-002,-4.761987194818160E-002
-3.713186593250521E-001, 7.119435018454577E-002
 1.765846250786073E-001,-5.167078202390172E-001
 3.919251072033576E+000, 2.731580892439468E-016
 8.463898327349600E-002,-1.769022020384163E-002
-1.693926416727003E-003, 3.186318202995109E-004
 2.972296739141557E-002, 2.470731324272232E-002
-4.971080240233405E-001,-2.233630050548641E-001
-3.048515562099071E-001, 2.236905085621603E-001
 8.463898327349656E-002, 1.769022020384197E-002
 4.020218577648722E+000,-3.623408630219666E-016
    </PARTIAL_DYN>
  </PARTIAL_MATRIX>
</Root>

