<?xml version="1.0"?>
<?iotk version="1.2.0"?>
<?iotk file_version="1.0"?>
<?iotk binary="F"?>
<?iotk qe_syntax="F"?>
<Root>
  <PM_HEADER>
    <DONE_IRR type="logical" size="1">
T
    </DONE_IRR>
  </PM_HEADER>
  <PARTIAL_MATRIX>
    <PARTIAL_DYN type="complex" size="36">
-3.910257688703887E+000,-5.612657179998081E-008
 2.763397336193601E-002,-6.590539752931155E-008
 1.814104283205931E-002, 2.630083061822930E-008
 0.000000000000000E+000, 0.000000000000000E+000
 0.000000000000000E+000, 0.000000000000000E+000
 0.000000000000000E+000, 0.000000000000000E+000
 2.740663119952230E-002, 5.353796164176823E-008
-3.930050554896992E+000,-5.643839381624992E-008
 1.012857819527759E-002,-1.230361895290728E-007
 0.000000000000000E+000, 0.000000000000000E+000
 0.000000000000000E+000, 0.000000000000000E+000
 0.000000000000000E+000, 0.000000000000000E+000
 2.150422772643709E-002, 5.613657103503625E-008
 9.214050159890616E-003, 8.279114638493792E-008
-3.957299805119443E+000,-6.093582609826228E-008
 0.000000000000000E+000, 0.000000000000000E+000
 0.000000000000000E+000, 0.000000000000000E+000
 0.000000000000000E+000, 0.000000000000000E+000
 3.651363957792204E-007, 3.771147359244889E-003
 7.018957244222385E-007, 1.686502469293646E-002
 2.365928716344112E-007,-1.208483037048877E-002
 0.000000000000000E+000, 0.000000000000000E+000
 0.000000000000000E+000, 0.000000000000000E+000
 0.000000000000000E+000, 0.000000000000000E+000
-5.338147273845593E-008, 1.195060885078767E-002
 3.698189797382567E-007,-1.928662305033762E-002
-4.930805599344390E-007,-1.026790552604924E-002
 0.000000000000000E+000, 0.000000000000000E+000
 0.000000000000000E+000, 0.000000000000000E+000
 0.000000000000000E+000, 0.000000000000000E+000
-1.229462238273426E-007, 2.121494326419189E-002
-1.726308906862075E-007,-1.323002386625784E-002
 2.744538468882167E-007, 3.611862374664606E-002
 0.000000000000000E+000, 0.000000000000000E+000
 0.000000000000000E+000, 0.000000000000000E+000
 0.000000000000000E+000, 0.000000000000000E+000
    </PARTIAL_DYN>
    <PARTIAL_ZUE type="complex" size="18">
 1.919502033921256E-006, 3.192437595317204E-001
 3.705620677139460E-006, 2.404381918315945E-001
 3.053453270426169E-006, 1.054207960265595E-001
 0.000000000000000E+000, 0.000000000000000E+000
 0.000000000000000E+000, 0.000000000000000E+000
 0.000000000000000E+000, 0.000000000000000E+000
-1.006915974795984E-006,-1.238669818480178E-001
-2.787546882448294E-006,-4.391040094915701E-001
-2.835569050163266E-008, 1.516277844431008E-002
 0.000000000000000E+000, 0.000000000000000E+000
 0.000000000000000E+000, 0.000000000000000E+000
 0.000000000000000E+000, 0.000000000000000E+000
-7.677648534369811E-008, 3.290330896859616E-001
-2.139043926572630E-006,-1.129808596863082E-001
 8.687768762973090E-007,-6.633188657986561E-002
 0.000000000000000E+000, 0.000000000000000E+000
 0.000000000000000E+000, 0.000000000000000E+000
 0.000000000000000E+000, 0.000000000000000E+000
    </PARTIAL_ZUE>
  </PARTIAL_MATRIX>
</Root>

