<?xml version="1.0"?>
<?iotk version="1.2.0"?>
<?iotk file_version="1.0"?>
<?iotk binary="F"?>
<?iotk qe_syntax="F"?>
<Root>
  <PM_HEADER>
    <DONE_IRR type="logical" size="1">
T
    </DONE_IRR>
  </PM_HEADER>
  <PARTIAL_MATRIX>
    <PARTIAL_DYN type="complex" size="36">
 3.692747010707045E+000,-3.191350066820056E-017
-5.336009412104659E-015,-4.207734818583694E-004
 1.195603945708390E-016,-1.959152824324356E-004
-2.573082805851223E-016,-1.338643154860891E-003
 7.346055860585135E-002,-4.035614025308046E-017
-2.612036150336923E-002,-1.377176665460075E-017
-4.808653475407709E-015, 4.207734818582490E-004
 6.876551859349033E+000,-3.190333627929568E-017
 6.232205074564570E-002,-5.039449625386222E-017
 4.609554389835242E-002, 1.093326354910475E-017
-1.487152686153320E-016,-2.552759660451639E-003
-1.491401403416748E-015, 4.758386872606805E-003
 2.305826970333547E-016, 1.959152824325788E-004
 6.232205074564545E-002,-4.287236700649135E-017
 3.327185507421047E+000,-1.266258428321791E-016
-3.145430786049853E-002, 5.461277849197116E-017
-3.454268121538817E-015,-1.267960863250532E-003
-2.266416221363698E-015,-1.119934918597823E-003
-2.573082805851223E-016, 1.338643154860889E-003
 4.609554389835187E-002, 4.674832456588346E-019
-3.145430786049865E-002, 4.942263700199319E-017
 3.235868735630778E+000,-2.246446744255686E-016
-8.491471414906471E-016, 7.756320839779111E-004
 3.155462002801812E-015, 6.400502967374290E-004
 7.346055860585103E-002,-4.561182120815790E-017
 2.814961534269161E-016, 2.552759660451643E-003
-3.717946089887292E-015, 1.267960863250577E-003
-9.462916561453483E-016,-7.756320839779026E-004
 4.884618193171978E+000,-1.060201754274543E-016
 5.050346698630950E-002,-1.760643029705738E-017
-2.612036150336918E-002,-2.412875585369096E-017
-1.546912554648006E-015,-4.758386872606961E-003
-2.266416221363698E-015, 1.119934918597815E-003
 3.433017758958101E-015,-6.400502967376052E-004
 5.050346698630955E-002,-1.472522127657933E-017
 4.846039781093372E+000,-2.452521682483177E-016
    </PARTIAL_DYN>
  </PARTIAL_MATRIX>
</Root>

