<?xml version="1.0"?>
<?iotk version="1.2.0"?>
<?iotk file_version="1.0"?>
<?iotk binary="F"?>
<?iotk qe_syntax="F"?>
<Root>
  <PM_HEADER>
    <DONE_IRR type="logical" size="1">
T
    </DONE_IRR>
  </PM_HEADER>
  <PARTIAL_MATRIX>
    <PARTIAL_DYN type="complex" size="36">
 0.000000000000000E+000, 0.000000000000000E+000
 0.000000000000000E+000, 0.000000000000000E+000
 0.000000000000000E+000, 0.000000000000000E+000
 1.416845166643445E-006,-2.605598020593382E-002
 1.401646804781442E-006, 8.976734308770041E-003
-1.090634108771166E-007, 1.705591510935807E-002
 0.000000000000000E+000, 0.000000000000000E+000
 0.000000000000000E+000, 0.000000000000000E+000
 0.000000000000000E+000, 0.000000000000000E+000
-3.222532494202152E-007, 1.388367915896406E-002
-6.172000209855172E-007, 1.729412721143290E-002
-1.727792859785617E-006,-2.628181148429090E-002
 0.000000000000000E+000, 0.000000000000000E+000
 0.000000000000000E+000, 0.000000000000000E+000
 0.000000000000000E+000, 0.000000000000000E+000
-5.880001599904445E-007,-1.173277688956897E-002
-1.385110755864564E-006,-1.785191614164955E-002
-3.878083910506275E-007,-8.560676815126180E-003
 0.000000000000000E+000, 0.000000000000000E+000
 0.000000000000000E+000, 0.000000000000000E+000
 0.000000000000000E+000, 0.000000000000000E+000
-3.481110757673768E+000, 5.387098769273531E-007
-6.308256601585547E-003, 9.195799025388150E-008
-8.172542745169994E-002,-1.347323861878449E-007
 0.000000000000000E+000, 0.000000000000000E+000
 0.000000000000000E+000, 0.000000000000000E+000
 0.000000000000000E+000, 0.000000000000000E+000
-6.307837907074673E-003,-2.037253888191321E-007
-3.426401225293618E+000, 4.821140541061328E-007
-2.097453967740957E-002, 1.208835216430370E-008
 0.000000000000000E+000, 0.000000000000000E+000
 0.000000000000000E+000, 0.000000000000000E+000
 0.000000000000000E+000, 0.000000000000000E+000
-8.172569796183728E-002, 2.999940710537068E-007
-2.097023939470456E-002, 7.532264615911796E-008
-3.459686149602534E+000, 5.855844423881673E-007
    </PARTIAL_DYN>
    <PARTIAL_ZUE type="complex" size="18">
 0.000000000000000E+000, 0.000000000000000E+000
 0.000000000000000E+000, 0.000000000000000E+000
 0.000000000000000E+000, 0.000000000000000E+000
-2.272351759927571E+000,-2.393995027822985E-006
-2.424099241650389E+000, 2.770661373692513E-006
-2.613250517617585E+000,-4.094518727525457E-006
 0.000000000000000E+000, 0.000000000000000E+000
 0.000000000000000E+000, 0.000000000000000E+000
 0.000000000000000E+000, 0.000000000000000E+000
 2.753959039737328E+000,-9.648478527317489E-006
-2.537284895801235E+000, 5.858846701655098E-006
-1.758420102394841E-001,-2.068888718308888E-006
 0.000000000000000E+000, 0.000000000000000E+000
 0.000000000000000E+000, 0.000000000000000E+000
 0.000000000000000E+000, 0.000000000000000E+000
 4.974502859340916E-001,-3.757640388756363E-006
 1.053609712104241E-001,-5.401118052608769E-007
-3.091982312421925E+000,-4.142666471449693E-006
    </PARTIAL_ZUE>
  </PARTIAL_MATRIX>
</Root>

