<?xml version="1.0"?>
<?iotk version="1.2.0"?>
<?iotk file_version="1.0"?>
<?iotk binary="F"?>
<?iotk qe_syntax="F"?>
<Root>
  <PM_HEADER>
    <DONE_IRR type="logical" size="1">
T
    </DONE_IRR>
  </PM_HEADER>
  <PARTIAL_MATRIX>
    <PARTIAL_DYN type="complex" size="36">
 0.000000000000000E+000, 0.000000000000000E+000
 0.000000000000000E+000, 0.000000000000000E+000
 0.000000000000000E+000, 0.000000000000000E+000
 0.000000000000000E+000, 0.000000000000000E+000
-7.098591820250484E-002, 9.939445115584348E-003
 3.351602741616636E-002,-7.212621447037976E-002
 0.000000000000000E+000, 0.000000000000000E+000
 0.000000000000000E+000, 0.000000000000000E+000
 0.000000000000000E+000, 0.000000000000000E+000
 0.000000000000000E+000, 0.000000000000000E+000
-6.019007778830254E-002,-7.013065285702300E-003
 1.348475621175304E-002,-6.876474508056885E-002
 0.000000000000000E+000, 0.000000000000000E+000
 0.000000000000000E+000, 0.000000000000000E+000
 0.000000000000000E+000, 0.000000000000000E+000
 0.000000000000000E+000, 0.000000000000000E+000
 2.241791654478804E-001, 1.469143769569555E-002
 2.679553764334803E-001,-2.044950326518454E-001
 0.000000000000000E+000, 0.000000000000000E+000
 0.000000000000000E+000, 0.000000000000000E+000
 0.000000000000000E+000, 0.000000000000000E+000
 0.000000000000000E+000, 0.000000000000000E+000
-1.889507185045919E-001,-3.433964241626241E-001
 2.190107085126592E-001, 1.136106483467183E-001
 0.000000000000000E+000, 0.000000000000000E+000
 0.000000000000000E+000, 0.000000000000000E+000
 0.000000000000000E+000, 0.000000000000000E+000
 0.000000000000000E+000, 0.000000000000000E+000
-3.694221533868227E+000,-1.105375894041271E-003
-1.363216538901933E-002, 1.852082642160391E-003
 0.000000000000000E+000, 0.000000000000000E+000
 0.000000000000000E+000, 0.000000000000000E+000
 0.000000000000000E+000, 0.000000000000000E+000
 0.000000000000000E+000, 0.000000000000000E+000
-1.163959302455812E-002, 5.398373542290003E-004
-3.698712183874307E+000, 1.240314507925779E-003
    </PARTIAL_DYN>
  </PARTIAL_MATRIX>
</Root>

