<?xml version="1.0"?>
<?iotk version="1.2.0"?>
<?iotk file_version="1.0"?>
<?iotk binary="F"?>
<?iotk qe_syntax="F"?>
<Root>
  <PM_HEADER>
    <DONE_IRR type="logical" size="1">
T
    </DONE_IRR>
  </PM_HEADER>
  <PARTIAL_MATRIX>
    <PARTIAL_DYN type="complex" size="36">
-3.926442242009641E+000,-3.473518036047272E-008
 2.798782469133698E-002, 2.186694184489031E-007
 1.826775155785269E-002,-2.354241138445451E-008
 0.000000000000000E+000, 0.000000000000000E+000
 0.000000000000000E+000, 0.000000000000000E+000
 0.000000000000000E+000, 0.000000000000000E+000
 2.775888116390089E-002,-2.065080024416081E-007
-3.946060963171851E+000,-1.042797332233342E-008
 1.030537003538839E-002,-5.418102973769103E-008
 0.000000000000000E+000, 0.000000000000000E+000
 0.000000000000000E+000, 0.000000000000000E+000
 0.000000000000000E+000, 0.000000000000000E+000
 2.182649818968175E-002, 9.975953350886047E-008
 9.318142910180963E-003, 3.620597956178161E-008
-3.973298505156563E+000,-9.286632124175488E-009
 0.000000000000000E+000, 0.000000000000000E+000
 0.000000000000000E+000, 0.000000000000000E+000
 0.000000000000000E+000, 0.000000000000000E+000
 1.957873118534417E-007, 3.764851528680181E-003
 1.014569965939599E-007, 1.651015967805330E-002
 1.490566268816385E-007,-1.197412016127825E-002
 0.000000000000000E+000, 0.000000000000000E+000
 0.000000000000000E+000, 0.000000000000000E+000
 0.000000000000000E+000, 0.000000000000000E+000
-2.723229052350486E-007, 1.169514045464396E-002
-3.374732668315339E-008,-1.899520048175808E-002
-1.251577472667631E-007,-1.021115059037192E-002
 0.000000000000000E+000, 0.000000000000000E+000
 0.000000000000000E+000, 0.000000000000000E+000
 0.000000000000000E+000, 0.000000000000000E+000
-1.636663177534056E-007, 2.138446808111811E-002
 1.038567832819040E-007,-1.344668793318877E-002
 3.455281764870415E-007, 3.594589733843168E-002
 0.000000000000000E+000, 0.000000000000000E+000
 0.000000000000000E+000, 0.000000000000000E+000
 0.000000000000000E+000, 0.000000000000000E+000
    </PARTIAL_DYN>
    <PARTIAL_ZUE type="complex" size="18">
 1.771738176898849E-006, 3.193659309653444E-001
 3.481117812504529E-006, 2.360639708606292E-001
 6.725692817086430E-007, 1.047904560189463E-001
 0.000000000000000E+000, 0.000000000000000E+000
 0.000000000000000E+000, 0.000000000000000E+000
 0.000000000000000E+000, 0.000000000000000E+000
 2.789000230663666E-006,-1.224272388932783E-001
 3.093320361440383E-006,-4.389508323947475E-001
-2.184810800054203E-006, 1.584914488168340E-002
 0.000000000000000E+000, 0.000000000000000E+000
 0.000000000000000E+000, 0.000000000000000E+000
 0.000000000000000E+000, 0.000000000000000E+000
 3.109831173810527E-008, 3.295506184135708E-001
-3.193652569684382E-006,-1.151030601483402E-001
 7.211711293488568E-007,-6.617786994809272E-002
 0.000000000000000E+000, 0.000000000000000E+000
 0.000000000000000E+000, 0.000000000000000E+000
 0.000000000000000E+000, 0.000000000000000E+000
    </PARTIAL_ZUE>
  </PARTIAL_MATRIX>
</Root>

