<?xml version="1.0"?>
<?iotk version="1.2.0"?>
<?iotk file_version="1.0"?>
<?iotk binary="F"?>
<?iotk qe_syntax="F"?>
<Root>
  <PM_HEADER>
    <DONE_IRR type="logical" size="1">
T
    </DONE_IRR>
  </PM_HEADER>
  <PARTIAL_MATRIX>
    <PARTIAL_DYN type="complex" size="36">
 5.823518705860545E+000,-4.514966393069991E-017
-4.090944152384033E-015,-3.425776512091671E-004
 1.746174296411893E-003, 1.773062323280836E-002
-6.036462308642360E-003, 1.337518138430019E-003
 4.237987118199087E-002,-2.057845310705422E-003
 5.114604314443073E-002, 3.845583971494596E-003
-4.313006080686436E-015, 3.425776512090955E-004
 4.537847173787707E+000,-2.559563073088571E-017
 1.373654365873479E-004,-5.115500048942223E-002
 4.278713862678182E-002, 3.988371984254519E-004
 5.917501067563635E-003,-6.628067920486206E-004
 1.770113072763413E-002, 1.828068539191860E-003
 1.746174296411622E-003,-1.773062323280833E-002
 1.373654365874306E-004, 5.115500048942215E-002
 4.422820418093055E+000,-1.792896375732836E-016
-1.044182210705052E-004,-7.107141539675811E-002
-7.065800057511774E-001, 1.790280785799057E-001
-4.372445571980140E-001, 9.771869709097426E-002
-6.036462308642355E-003,-1.337518138429980E-003
 4.278713862678171E-002,-3.988371984255902E-004
-1.044182210703974E-004, 7.107141539675817E-002
 4.375755287897556E+000,-8.290094732574995E-017
 2.425598269723613E-003,-4.464091915401157E-001
-2.671318546951065E-002, 7.151805390811616E-001
 4.237987118199079E-002, 2.057845310705390E-003
 5.917501067563607E-003, 6.628067920486427E-004
-7.065800057511774E-001,-1.790280785799057E-001
 2.425598269723759E-003, 4.464091915401157E-001
 3.820708816018600E+000,-2.284900366923701E-018
-7.276936462791865E-002,-1.656650613252630E-003
 5.114604314443066E-002,-3.845583971494593E-003
 1.770113072763412E-002,-1.828068539191645E-003
-4.372445571980142E-001,-9.771869709097404E-002
-2.671318546951066E-002,-7.151805390811616E-001
-7.276936462791865E-002, 1.656650613252585E-003
 3.866752546176168E+000,-9.794953727335262E-017
    </PARTIAL_DYN>
  </PARTIAL_MATRIX>
</Root>

