<?xml version="1.0"?>
<?iotk version="1.2.0"?>
<?iotk file_version="1.0"?>
<?iotk binary="F"?>
<?iotk qe_syntax="F"?>
<Root>
  <PM_HEADER>
    <DONE_IRR type="logical" size="1">
T
    </DONE_IRR>
  </PM_HEADER>
  <PARTIAL_MATRIX>
    <PARTIAL_DYN type="complex" size="36">
 0.000000000000000E+000, 0.000000000000000E+000
 0.000000000000000E+000, 0.000000000000000E+000
 0.000000000000000E+000, 0.000000000000000E+000
 8.659890278484017E-008,-5.706853344837911E-003
-3.201741853205153E-007,-1.505476090107223E-002
-1.079090638169029E-007,-1.761515908014416E-002
 0.000000000000000E+000, 0.000000000000000E+000
 0.000000000000000E+000, 0.000000000000000E+000
 0.000000000000000E+000, 0.000000000000000E+000
 7.770402202927906E-008,-1.999175394690598E-002
 1.036767057274735E-007, 1.964693523177243E-002
 1.558184545202498E-007, 1.138671295150841E-002
 0.000000000000000E+000, 0.000000000000000E+000
 0.000000000000000E+000, 0.000000000000000E+000
 0.000000000000000E+000, 0.000000000000000E+000
 3.510972433756754E-007, 1.195491375659502E-002
-5.054293192308101E-008, 9.500886082267462E-003
 2.263557990107856E-007,-3.372566278784486E-002
 0.000000000000000E+000, 0.000000000000000E+000
 0.000000000000000E+000, 0.000000000000000E+000
 0.000000000000000E+000, 0.000000000000000E+000
-3.609063090009187E+000,-2.484960283185625E-008
-3.101669101029239E-003, 5.377824414325343E-008
-5.310619234176557E-002, 2.931985030720318E-008
 0.000000000000000E+000, 0.000000000000000E+000
 0.000000000000000E+000, 0.000000000000000E+000
 0.000000000000000E+000, 0.000000000000000E+000
-3.104138173920131E-003,-4.693429383379771E-008
-3.496837727035729E+000,-1.570735022137958E-008
 1.001716761908215E-002, 9.811071629390831E-008
 0.000000000000000E+000, 0.000000000000000E+000
 0.000000000000000E+000, 0.000000000000000E+000
 0.000000000000000E+000, 0.000000000000000E+000
-5.310733970501204E-002,-1.878862774193426E-008
 1.002340010472345E-002,-1.030968118127400E-007
-3.480085734614955E+000,-2.926841720485592E-008
    </PARTIAL_DYN>
    <PARTIAL_ZUE type="complex" size="18">
 0.000000000000000E+000, 0.000000000000000E+000
 0.000000000000000E+000, 0.000000000000000E+000
 0.000000000000000E+000, 0.000000000000000E+000
-3.412150725427349E+000,-6.923603702179976E-007
 1.936155402964766E+000, 7.360701461301231E-007
-1.608147527392932E+000,-9.082439731506598E-007
 0.000000000000000E+000, 0.000000000000000E+000
 0.000000000000000E+000, 0.000000000000000E+000
 0.000000000000000E+000, 0.000000000000000E+000
 2.091328644520650E+000,-2.916659459306032E-008
 2.832065523422748E+000, 6.758086291636301E-007
-1.272867559031337E+000,-7.601203771946791E-007
 0.000000000000000E+000, 0.000000000000000E+000
 0.000000000000000E+000, 0.000000000000000E+000
 0.000000000000000E+000, 0.000000000000000E+000
-6.905164587500023E-001,-7.908826085056807E-007
-2.601919453715354E-001, 1.850627846655855E-007
-3.051412438903629E+000, 2.417097414673720E-007
    </PARTIAL_ZUE>
  </PARTIAL_MATRIX>
</Root>

